explerr-0.1.0.dist-info/METADATA
explerr-0.1.0.dist-info/WHEEL
explerr-0.1.0.dist-info/entry_points.txt
explerr-0.1.0.dist-info/licenses/LICENSE
explerr/__init__.py
explerr/cli.py
explerr/exceptions.py
explerr-0.1.0.dist-info/RECORD
