Metadata-Version: 2.4
Name: explerr
Version: 0.1.0
Summary: Error explainer using LLMs
Author-Email: Honghua Dong <dhh19951@gmail.com>
License-Expression: MIT
Requires-Python: >=3.8
Requires-Dist: applang>=0.1.5
Requires-Dist: rich
